key_value_ds/__init__.py
key_value_ds/config.py
key_value_ds/datastore.py
tests/test_datastore.py
tests/test_get_instance.py
key_value_ds-1.0.3.dist-info/LICENSE.txt
key_value_ds-1.0.3.dist-info/METADATA
key_value_ds-1.0.3.dist-info/WHEEL
key_value_ds-1.0.3.dist-info/top_level.txt
key_value_ds-1.0.3.dist-info/RECORD
