Metadata-Version: 2.1
Name: key-value-ds
Version: 1.0.3
Summary: A key value datastore which stores data locally in a memory-mapped file.
Home-page: https://github.com/syogaraj/key-value-ds
Author: Yogaraj.S
Author-email: yogarajsivaprakasam@gmail.com
License: MIT
Download-URL: https://github.com/syogaraj/key-value-ds/releases/tag/v1.0.3
Platform: UNKNOWN
Classifier: Development Status :: 5 - Production/Stable
Classifier: Topic :: Utilities
Classifier: License :: OSI Approved :: MIT License
Provides-Extra: dev
Requires-Dist: pytest ; extra == 'dev'
Requires-Dist: wheel ; extra == 'dev'
